pz_server/__init__.py
pz_server/api.py
pz_server/catalog.py
pz_server/core.py
pz_server_lib-0.1.7.dist-info/LICENSE
pz_server_lib-0.1.7.dist-info/METADATA
pz_server_lib-0.1.7.dist-info/WHEEL
pz_server_lib-0.1.7.dist-info/top_level.txt
pz_server_lib-0.1.7.dist-info/RECORD
