Metadata-Version: 2.1
Name: pz-server-lib
Version: 0.1.7
Summary: Python library to access the Photo-z Server database hosted by the Brazilian LSST IDAC at LIneA. 
Home-page: https://github.com/linea-it/pz-server-lib
License: MIT
Requires-Python: >=3.9, <4
License-File: LICENSE
Requires-Dist: numpy (<1.24,>=1.23)
Requires-Dist: pandas (>=1.2.0)
Requires-Dist: requests (>=2.23.0)
Requires-Dist: astropy (>=5.0.0)
Requires-Dist: matplotlib (>=3.6.0)
Requires-Dist: tables-io (>=0.7.9)
Requires-Dist: Jinja2 (>=3.1.2)
Requires-Dist: ipython (>=8.5.0)
